.gitignore
IodSymbolize.cmake
MANIFEST.in
README.md
requirements.txt
setup.cfg
setup.py
iod_symbolizer.egg-info/PKG-INFO
iod_symbolizer.egg-info/SOURCES.txt
iod_symbolizer.egg-info/dependency_links.txt
iod_symbolizer.egg-info/entry_points.txt
iod_symbolizer.egg-info/not-zip-safe
iod_symbolizer.egg-info/requires.txt
iod_symbolizer.egg-info/top_level.txt
symbolizer/__init__.py
symbolizer/cli.py
symbolizer/config.py
symbolizer/histogram.py
symbolizer/parser.py
symbolizer/templates.py
symbolizer/version.py
test/__init__.py
test/sample.py
test/test_symbolizer.py